Histropy/Histropy.py
Histropy/ImageCalculator.py
Histropy/InterHist.py
Histropy/__init__.py
Histropy/data/from acta paper 512 square 0.1 Gaussian.jpg
Histropy/data/from acta paper 512 square no noise.jpg
Histropy/data/p1 of from acta paper 512 square 0.1 Gaussian.jpg
Histropy/data/p2 of from acta paper 512 square 0.1 Gaussian.jpg
Histropy/data/p4 of from acta paper 512 square 0.1 Gaussian.jpg
Histropy/data/p4g of from acta paper 512 square 0.1 Gaussian.jpg
Histropy/tests/Histropy_Examples.py
histropy-0.1.6.dist-info/METADATA
histropy-0.1.6.dist-info/WHEEL
histropy-0.1.6.dist-info/licenses/LICENSE
histropy-0.1.6.dist-info/RECORD
