Metadata-Version: 2.4
Name: Histropy
Version: 0.1.6
Summary: An interactive Python-based program for the quantification of selected features of two-dimensional (2D) images/patterns (in either JPG/JPEG, PNG, GIF, BMP, or baseline TIF/TIFF formats) by means of calculations based on the pixel intensities in this data, their histograms, and user-selected sections of those histograms.
Project-URL: Homepage, https://github.com/SMenon-14/Histropy
Author-email: Sagarika Menon <sagarikamenon14@gmail.com>
License: MIT License
License-File: LICENSE
Classifier: License :: OSI Approved :: MIT License
Classifier: Operating System :: OS Independent
Classifier: Programming Language :: Python :: 3
Requires-Python: >=3.12
Requires-Dist: easygui>=0.98.3
Requires-Dist: matplotlib>=3.10.1
Requires-Dist: numpy>=2.2.4
Requires-Dist: tabulate>=0.9.0
